HISTORY.rst
LICENSE
MANIFEST.in
README.md
setup.py
business_rules/__init__.py
business_rules/actions.py
business_rules/engine.py
business_rules/fields.py
business_rules/operators.py
business_rules/six.py
business_rules/utils.py
business_rules/variables.py
business_rules_extra.egg-info/PKG-INFO
business_rules_extra.egg-info/SOURCES.txt
business_rules_extra.egg-info/dependency_links.txt
business_rules_extra.egg-info/top_level.txt